{
    "display": {
        "frame": "challenge",
        "icon": {
            "item": "minecraft:andesite"
        },
        "title": "Bloc tier 2-2",
        "description": "Mine 250000  blocs d'andesite"
    },
    "parent": "custom:ultra/granite",
    "criteria": {
        "basalt": {
            "trigger": "location",
			"conditions": {
				"player": {
					"player": {
						"stats": [{
							"type": "mined",
							"stat": "minecraft:andesite",
							"value": {
								"min": 250000
							}
						}]
					}
				}
			}
        }
    }
}
