{
	"display": {
		"frame": "challenge",
		"icon": {
			"item": "minecraft:torch"
		},
		"title": "Torchez-moi tout ça",
		"description": "Remplissez votre inventaire de torche pour sécuriser la zone"
	},
	"parent": "custom:forestry/charcoal",
	"criteria": {
		"full of torch": {
            "trigger": "minecraft:inventory_changed",
            "conditions": {
                "items": [
                    {
                        "item": "minecraft:torch",
                        "count": {
                            "min": 2304,
                            "max": 2304
                        }
                    }
                ],
                "slots": {
                    "full": 36
                }
            }
        }
    },
    "requirements": [
        [
            "full of torch"
        ]
    ]
}